[
  {
    "no": 28,
    "photo": "https://tqklhszfkvzk6518638.cdn.ntruss.com/product/8801382124849.jpg",
    "name": "웅진)하늘보리P500ml",
    "price": 1800
  },
  {
    "no": 50,
    "photo": "https://tqklhszfkvzk6518638.cdn.ntruss.com/product/8808244201045.jpg",
    "name": "광동)제주삼다수P2L",
    "price": 1950
  },
  {
    "no": 58,
    "photo": "https://tqklhszfkvzk6518638.cdn.ntruss.com/product/8801223013202.jpg",
    "name": "일화)호박팥차P500ml",
    "price": 2000
  },
  {
    "no": 69,
    "photo": "https://tqklhszfkvzk6518638.cdn.ntruss.com/product/8801094342623.jpg",
    "name": "코카)태양의보리차P500",
    "price": 2000
  },
  {
    "no": 81,
    "photo": "https://tqklhszfkvzk6518638.cdn.ntruss.com/product/8801056076542.jpg",
    "name": "롯데)초가을우엉차P500ml",
    "price": 1600
  },

  {
    "no": 89,
    "photo": "https://tqklhszfkvzk6518638.cdn.ntruss.com/product/8801382148203.jpg",
    "name": "웅진)하늘보리캔340ml",
    "price": 1500
  },
  {
    "no": 92,
    "photo": "https://tqklhszfkvzk6518638.cdn.ntruss.com/product/8801056227555.jpg",
    "name": "롯데)더하다우엉차P500ml",
    "price": 2000
  },
  {
    "no": 105,
    "photo": "https://tqklhszfkvzk6518638.cdn.ntruss.com/product/8809296885009.jpg",
    "name": "팔도)뽀로로보리차P220ml",
    "price": 1300
  },
  {
    "no": 106,
    "photo": "https://tqklhszfkvzk6518638.cdn.ntruss.com/product/8808244201014.jpg",
    "name": "광동)제주삼다수P500ml",
    "price": 1100
  },
  {
    "no": 167,
    "photo": "https://tqklhszfkvzk6518638.cdn.ntruss.com/product/8801043022781.jpg",
    "name": "농심)백산수P500ml",
    "price": 950
  },
  {
    "no": 177,
    "photo": "https://tqklhszfkvzk6518638.cdn.ntruss.com/product/8809685981039.jpg",
    "name": "티젠)콤부차레몬P340ml",
    "price": 2000
  },
  {
    "no": 202,
    "photo": "https://tqklhszfkvzk6518638.cdn.ntruss.com/product/8801056237493.jpg",
    "name": "롯데)더시원아이시스2L6입",
    "price": 3600
  },
  {
    "no": 209,
    "photo": "https://tqklhszfkvzk6518638.cdn.ntruss.com/product/8801094342630.jpg",
    "name": "코카)태양의옥수수차P500",
    "price": 2000
  },
  {
    "no": 233,
    "photo": "https://tqklhszfkvzk6518638.cdn.ntruss.com/product/8809685981046.jpg",
    "name": "티젠)콤부차피치P340ml",
    "price": 2000
  },
  {
    "no": 246,
    "photo": "https://tqklhszfkvzk6518638.cdn.ntruss.com/product/8801001235215.jpg",
    "name": "하이트)석수2L6입",
    "price": 3600
  },
  {
    "no": 266,
    "photo": "https://tqklhszfkvzk6518638.cdn.ntruss.com/product/8801056227371.jpg",
    "name": "롯데)더하다옥수수P500ml",
    "price": 2000
  },
  {
    "no": 280,
    "photo": "https://tqklhszfkvzk6518638.cdn.ntruss.com/product/8806002009957.jpg",
    "name": "광동)힘찬헛개차P500ml",
    "price": 2000
  },
  {
    "no": 283,
    "photo": "https://tqklhszfkvzk6518638.cdn.ntruss.com/product/8801097138711.jpg",
    "name": "동아)나랑드콤부차캔245ml",
    "price": 1600
  },
  {
    "no": 305,
    "photo": "https://tqklhszfkvzk6518638.cdn.ntruss.com/product/8801001235765.jpg",
    "name": "HEYROO미네랄워터P2L",
    "price": 1300
  },
  {
    "no": 307,
    "photo": "https://tqklhszfkvzk6518638.cdn.ntruss.com/product/8801069174020.jpg",
    "name": "남양)17차P500ml",
    "price": 1800
  },
  {
    "no": 321,
    "photo": "https://tqklhszfkvzk6518638.cdn.ntruss.com/product/8801382143123.jpg",
    "name": "웅진)코코몽하늘보리200ml",
    "price": 1400
  },
  {
    "no": 360,
    "photo": "https://tqklhszfkvzk6518638.cdn.ntruss.com/product/8801382135036.jpg",
    "name": "웅진)오곡누룽지P500ml",
    "price": 1800
  },
  {
    "no": 366,
    "photo": "https://tqklhszfkvzk6518638.cdn.ntruss.com/product/4901085003800.jpg",
    "name": "농심)오이오차녹차P500",
    "price": 2200
  },
  {
    "no": 414,
    "photo": "https://tqklhszfkvzk6518638.cdn.ntruss.com/product/8806002009957.jpg",
    "name": "광동)힘찬헛개차P500ml",
    "price": 2000
  },
  {
    "no": 431,
    "photo": "https://tqklhszfkvzk6518638.cdn.ntruss.com/product/8801056171339.jpg",
    "name": "롯)아이시스에코500ml*20",
    "price": 18000
  },
  {
    "no": 434,
    "photo": "https://tqklhszfkvzk6518638.cdn.ntruss.com/product/8801001238179.jpg",
    "name": "하이트)블랙보리라이트520",
    "price": 1800
  },
  {
  "no": 441,
  "photo": "https://tqklhszfkvzk6518638.cdn.ntruss.com/product/8801007171210.jpg",
  "name": "HK)헛개수P500ml",
  "price": 2200
  },
  {
    "no": 465,
    "photo": "https://tqklhszfkvzk6518638.cdn.ntruss.com/product/8801223100179.jpg",
    "name": "일화)초정탄산수P500ml",
    "price": 1500
  },
  {
    "no": 467,
    "photo": "https://tqklhszfkvzk6518638.cdn.ntruss.com/product/8801056075385.jpg",
    "name": "HEYROO미네랄워터P1L",
    "price": 1000
  },
  {
    "no": 471,
    "photo": "https://tqklhszfkvzk6518638.cdn.ntruss.com/product/8801382124849.jpg",
    "name": "웅진)하늘보리P500ml",
    "price": 1800
  },
  {
    "no": 545,
    "photo": "https://tqklhszfkvzk6518638.cdn.ntruss.com/product/8809422041125.jpg",
    "name": "HK)새싹보리P500ml",
    "price": 2200
  },
  {
    "no": 567,
    "photo": "https://tqklhszfkvzk6518638.cdn.ntruss.com/product/8806002020174.jpg",
    "name": "광동)밀싹보리차P500ml",
    "price": 2000
  },
  {
    "no": 568,
    "photo": "https://tqklhszfkvzk6518638.cdn.ntruss.com/product/8801382145769.jpg",
    "name": "웅진)결명자차P500ml",
    "price": 1800
  },
  {
    "no": 652,
    "photo": "https://tqklhszfkvzk6518638.cdn.ntruss.com/product/8808244101086.jpg",
    "name": "광동)삼다수그린500P20입",
    "price": 19000
  },
  {
    "no": 660,
    "photo": "https://tqklhszfkvzk6518638.cdn.ntruss.com/product/8801001238049.jpg",
    "name": "하이트)블랙보리P520ml",
    "price": 1800
  },
  {
    "no": 670,
    "photo": "https://tqklhszfkvzk6518638.cdn.ntruss.com/product/8803186200125.jpg",
    "name": "청정)몽베스트P500ml",
    "price": 1100
  },
  {
    "no": 679,
    "photo": "https://tqklhszfkvzk6518638.cdn.ntruss.com/product/8808024030803.jpg",
    "name": "쟈뎅)제주청보리차P500ml",
    "price": 2000
  },
  {
    "no": 692,
    "photo": "https://tqklhszfkvzk6518638.cdn.ntruss.com/product/8801105000313.jpg",
    "name": "해태)평창수P2L",
    "price": 1700
  },
  {
    "no": 714,
    "photo": "https://tqklhszfkvzk6518638.cdn.ntruss.com/product/8801105915303.jpg",
    "name": "해태)평창수프리미엄500ml",
    "price": 1000
  },
  {
    "no": 797,
    "photo": "https://tqklhszfkvzk6518638.cdn.ntruss.com/product/8801068081374.jpg",
    "name": "삼립)지리산수P500ml",
    "price": 950
  },
  {
    "no": 803,
    "photo": "https://tqklhszfkvzk6518638.cdn.ntruss.com/product/8801056049881.jpg",
    "name": "롯데)아이시스8.0P500ml",
    "price": 1100
  },
  {
    "no": 820,
    "photo": "https://tqklhszfkvzk6518638.cdn.ntruss.com/product/8806002009391.jpg",
    "name": "광동)힘찬헛개차1.5L",
    "price": 3000
  },
  {
    "no": 821,
    "photo": "https://tqklhszfkvzk6518638.cdn.ntruss.com/product/8801382148449.jpg",
    "name": "웅진)옥수수수염차500ml",
    "price": 1800
  },
  {
    "no": 848,
    "photo": "https://tqklhszfkvzk6518638.cdn.ntruss.com/product/8806002005805.jpg",
    "name": "광동)옥수수수염차1.5L",
    "price": 3000
  },
  {
    "no": 866,
    "photo": "https://tqklhszfkvzk6518638.cdn.ntruss.com/product/8801097239814.jpg",
    "name": "동아)나랑드콤부차P400ml",
    "price": 2500
  },
  {
    "no": 876,
    "photo": "https://tqklhszfkvzk6518638.cdn.ntruss.com/product/8801382131038.jpg",
    "name": "웅진)하늘보리1.5L",
    "price": 3000
  },
  {
    "no": 880,
    "photo": "https://tqklhszfkvzk6518638.cdn.ntruss.com/product/8801056169817.jpg",
    "name": "HEYROO미네랄워터P500ml",
    "price": 700
  },
  {
    "no": 913,
    "photo": "https://tqklhszfkvzk6518638.cdn.ntruss.com/product/8801043020473.jpg",
    "name": "농심)백산수P2L",
    "price": 1700
  },
  {
    "no": 935,
    "photo": "https://tqklhszfkvzk6518638.cdn.ntruss.com/product/8801117070007.jpg",
    "name": "오리온)제주용암수P530ml",
    "price": 1000
  },
  {
    "no": 942,
    "photo": "https://tqklhszfkvzk6518638.cdn.ntruss.com/product/8801056049904.jpg",
    "name": "롯데)아이시스8.0P2L",
    "price": 1950
  },
  {
    "no": 943,
    "photo": "https://tqklhszfkvzk6518638.cdn.ntruss.com/product/8806002006437.jpg",
    "name": "광동)옥수수수염P500ml",
    "price": 2000
  },
  {
    "no": 972,
    "photo": "https://tqklhszfkvzk6518638.cdn.ntruss.com/product/8801094342609.jpg",
    "name": "코카)태양의마테차P500ml",
    "price": 1400
  },
  {
    "no": 990,
    "photo": "https://tqklhszfkvzk6518638.cdn.ntruss.com/product/8806002020136.jpg",
    "name": "광동)흑미차500ml",
    "price": 2000
  },
  {
    "no": 1024,
    "photo": "http://cdn2.bgfretail.com/bgfbrand/files/product/297B572F71F04C39ABDC195218CA5A3A.jpg",
    "name": "일동)카카오닙스차P500ml",
    "price": 1700
  },
  {
    "no": 1028,
    "photo": "https://tqklhszfkvzk6518638.cdn.ntruss.com/product/3068320024400.jpg",
    "name": "롯데)에비앙P500ml",
    "price": 2200
  },
  {
  "no": 1044,
  "photo": "https://tqklhszfkvzk6518638.cdn.ntruss.com/product/8801007223742.jpg",
  "name": "HK)헛개수1.5L",
  "price": 3000
  },
  {
    "no": 1051,
    "photo": "https://tqklhszfkvzk6518638.cdn.ntruss.com/product/8801068880212.jpg",
    "name": "삼립)오생수P320ml",
    "price": 1000
  },
  {
    "no": 1064,
    "photo": "https://tqklhszfkvzk6518638.cdn.ntruss.com/product/8801056234614.jpg",
    "name": "롯데)더하다헛개차P500ml",
    "price": 2000
  },
  {
    "no": 1072,
    "photo": "https://tqklhszfkvzk6518638.cdn.ntruss.com/product/8801001238056.jpg",
    "name": "하이트)블랙보리1.5L",
    "price": 3000
  },
  {
  "no": 1092,
  "photo": "https://tqklhszfkvzk6518638.cdn.ntruss.com/product/8801047289685.jpg",
  "name": "동원)양반오미자차500ml",
  "price": 2200
  },
  {
    "no": 1104,
    "photo": "https://tqklhszfkvzk6518638.cdn.ntruss.com/product/8809422041729.jpg",
    "name": "HK)헛개수이엑스P500ml",
    "price": 3000
  }
]